go_cli-0.1.1.dist-info/RECORD
go_cli-0.1.1.dist-info/DESCRIPTION.rst
go_cli-0.1.1.dist-info/METADATA
go_cli-0.1.1.dist-info/WHEEL
go_cli-0.1.1.dist-info/metadata.json
go_cli-0.1.1.dist-info/top_level.txt
go_cli-0.1.1.dist-info/entry_points.txt
go_cli/main.py
go_cli/__init__.py
go_cli/send.py
go_cli/export_contacts.py
go_cli/tests/test_send.py
go_cli/tests/test_export_contacts.py
go_cli/tests/utils.py
go_cli/tests/test_main.py
go_cli/tests/__init__.py
