Metadata-Version: 2.0
Name: go-cli
Version: 0.1.1
Summary: A command-line interface for Vumi Go's HTTP APIs
Home-page: http://github.com/praekelt/go-cli
Author: Praekelt Foundation
Author-email: dev@praekeltfoundation.org
License: BSD
Platform: UNKNOWN
Classifier: Development Status :: 4 - Beta
Classifier: Intended Audience :: Developers
Classifier: License :: OSI Approved :: BSD License
Classifier: Operating System :: POSIX
Classifier: Programming Language :: Python
Requires-Dist: go-http
Requires-Dist: click
